cmdai/__init__.py
cmdai/cli.py
cmdai/config.py
cmdai/models.py
cmdai/providers/__init__.py
cmdai/providers/mistral.py
cmdai/providers/openai.py
cmdai/providers/venice.py
cmdchat-0.1.8.dist-info/METADATA
cmdchat-0.1.8.dist-info/WHEEL
cmdchat-0.1.8.dist-info/entry_points.txt
cmdchat-0.1.8.dist-info/top_level.txt
cmdchat-0.1.8.dist-info/RECORD
