Metadata-Version: 2.2
Name: cmdchat
Version: 0.1.8
Summary: A command-line AI tool supporting OpenAI, Mistral, and Venice.
Home-page: https://github.com/skilledkitten/cmdai
Author: skilledkitten
Author-email: skilledkitten@proton.metadata.org
Classifier: Programming Language :: Python :: 3
Classifier: License :: OSI Approved :: MIT License
Classifier: Operating System :: OS Independent
Requires-Python: >=3.7
Requires-Dist: requests
Requires-Dist: openai==1.61.0
